pymyku/__init__.py
pymyku/attribute.py
pymyku/constant.py
pymyku/exception.py
pymyku/pymyku.py
pymyku/requests.py
pymyku/type.py
pymyku/url.py
pymyku/utils.py
pymyku-0.3.0.dist-info/LICENSE.md
pymyku-0.3.0.dist-info/METADATA
pymyku-0.3.0.dist-info/WHEEL
pymyku-0.3.0.dist-info/top_level.txt
pymyku-0.3.0.dist-info/RECORD
