Metadata-Version: 2.1
Name: pymyku
Version: 0.3.0
Summary: Python MyKU API Wrapper
Home-page: https://github.com/phusitsom/pymyku
Author: phusitsom
Author-email: phusitsom@gmail.com
Project-URL: Documentation, https://pymyku.readthedocs.io
Classifier: Natural Language :: English
Classifier: Intended Audience :: Developers
Classifier: Programming Language :: Python
Classifier: Programming Language :: Python :: 3
Classifier: Programming Language :: Python :: 3.6
Classifier: Programming Language :: Python :: 3.7
Classifier: Programming Language :: Python :: 3.8
Classifier: Programming Language :: Python :: 3.9
Classifier: Programming Language :: Python :: 3.10
Requires-Python: >=3.6
Provides-Extra: docs
License-File: LICENSE.md
